cutia/__init__.py
cutia/adapters/__init__.py
cutia/adapters/dspy/__init__.py
cutia/adapters/dspy_adapter/__init__.py
cutia/adapters/dspy_adapter/bounded_chat_adapter.py
cutia/adapters/dspy_adapter/dspy_adapter.py
cutia/examples/.env.example
cutia/examples/.gitignore
cutia/examples/README.md
cutia/examples/__init__.py
cutia/examples/strawberry.py
cutia/py.typed
cutia/utils/__init__.py
cutia/utils/logging_utils.py
cutia-0.0.2.dist-info/WHEEL
cutia-0.0.2.dist-info/METADATA
cutia-0.0.2.dist-info/RECORD
