Metadata-Version: 2.3
Name: cutia
Version: 0.0.2
Summary: Tree-based prompt compression library using cut-then-transform strategy for LLM applications
Keywords: prompt-compression,llm,dspy,nlp,optimization,ai,machine-learning
Author: Aleksei Leshikhin
Author-email: Aleksei Leshikhin <napmany@outlook.com>
Classifier: Development Status :: 3 - Alpha
Classifier: Intended Audience :: Developers
Classifier: Intended Audience :: Science/Research
Classifier: License :: OSI Approved :: MIT License
Classifier: Operating System :: OS Independent
Classifier: Programming Language :: Python :: 3
Classifier: Programming Language :: Python :: 3.10
Classifier: Programming Language :: Python :: 3.11
Classifier: Programming Language :: Python :: 3.12
Classifier: Programming Language :: Python :: 3.13
Classifier: Programming Language :: Python :: 3.14
Classifier: Topic :: Scientific/Engineering :: Artificial Intelligence
Classifier: Topic :: Text Processing :: Linguistic
Classifier: Typing :: Typed
Requires-Dist: cutia[test] ; extra == 'dev'
Requires-Dist: ruff>=0.3.0 ; extra == 'dev'
Requires-Dist: pre-commit ; extra == 'dev'
Requires-Dist: pyright>=1.1.0 ; extra == 'dev'
Requires-Dist: datasets>=2.14.0 ; extra == 'full'
Requires-Dist: python-dotenv>=1.0.0 ; extra == 'full'
Requires-Dist: cutia[full] ; extra == 'test'
Requires-Dist: pytest>=8.0.0 ; extra == 'test'
Requires-Dist: dspy>=3.0.0 ; extra == 'test'
Requires-Python: >=3.10, <3.15
Project-URL: Documentation, https://github.com/napmany/cutia#readme
Project-URL: Homepage, https://github.com/napmany/cutia
Project-URL: Issues, https://github.com/napmany/cutia/issues
Project-URL: Repository, https://github.com/napmany/cutia
Provides-Extra: dev
Provides-Extra: full
Provides-Extra: test
